{
  "cards": [
    {
      "id": 1,
      "name": "强制静音卡",
      "rarity": "common",
      "description": "出示此卡后，我同意停止说话60秒，并接受你的一个拥抱或亲吻。",
      "usage": "当争吵激烈，我听不进任何话时，立即出示此卡并上前拥抱我。",
      "tips": "拥抱要真诚有力，不要犹豫。如果一次不成，可以间隔半小时后再试一次。此卡一周可用3次。",
      "quote": "我知道我生气时会开启‘屏蔽模式’，你的拥抱就是关闭它的开关。",
      "isSearched": false
    },
    {
      "id": 2,
      "name": "万能台阶卡",
      "rarity": "legend",
      "description": "这是我给你的终极解决方案卡。使用此卡，我会给出一个明确的和解方式。",
      "usage": "当你使出浑身解数都哄不好我时，出示此卡，我会告诉你该怎么做。",
      "tips": "请谨慎使用，这是最后的法宝。",
      "quote": "当你用这张卡时，我会放下情绪，告诉你我的真实需求。",
      "isSearched": false
    },
    {
      "id": 3,
      "name": "鬼脸模仿卡",
      "rarity": "common",
      "description": "出示此卡后，你需要做一个滑稽鬼脸，直到我笑出来为止。",
      "usage": "在气氛稍微缓和但我还板着脸时使用，效果最佳。",
      "tips": "不用在乎面子，我的笑容最重要。可以提前准备几个招牌动作。",
      "quote": "只要你愿意逗我笑，我就愿意让不开心过去。",
      "isSearched": false
    },
    {
      "id": 4,
      "name": "休战白旗卡",
      "rarity": "rare",
      "description": "出示此卡，我同意暂时休战，我们一起去做点别的事情转换心情。",
      "usage": "当争吵陷入循环没有结果时，出示此卡暂停争论。",
      "tips": "转移注意力是关键，可以提议一起看个电影或玩个游戏。",
      "quote": "我同意暂时休战，让我们都冷静一下再好好聊。",
      "isSearched": false
    },
    {
      "id": 5,
      "name": "投喂卡",
      "rarity": "rare",
      "description": "使用此卡后，你要为我点一份最爱吃的外卖或亲自下厨。",
      "usage": "当我生气时间较长，可能饿了或需要安慰时使用。",
      "tips": "记得备注暖心留言，甜食通常有奇效。",
      "quote": "美食确实能治愈我的坏心情，特别是你用心准备的。",
      "isSearched": false
    },
    {
      "id": 6,
      "name": "闭嘴按摩卡",
      "rarity": "rare",
      "description": "使用此卡后，你可以为我按摩10分钟，期间不许提惹我生气的事。",
      "usage": "当我看起来疲惫或需要放松时使用。",
      "tips": "搭配我喜欢的音乐或香氛效果更佳。专心按摩不要说话。",
      "quote": "你的按摩能让我身体放松，情绪也会慢慢平复。",
      "isSearched": false
    },
    {
      "id": 7,
      "name": "免死金牌卡",
      "rarity": "legend",
      "description": "使用此卡可以抵消一个小错误。",
      "usage": "用于那些确实做错了但不值得长期争吵的小事。",
      "tips": "不要用于原则性问题。用后要真的改进，否则会失效。",
      "quote": "用这张卡原谅你的小过错，但下次要更细心哦。",
      "isSearched": false
    },
    {
      "id": 8,
      "name": "手写检讨卡",
      "rarity": "rare",
      "description": "使用此卡后，你需要写一份200字的检讨，夸我3个优点，分析自己1个缺点。",
      "usage": "当你确实做错了，需要认真表达歉意时使用。",
      "tips": "字迹工整，感情真挚。写完后要声情并茂地朗读。",
      "quote": "文字能让我看到你的真心，感受到你的重视。",
      "isSearched": false
    },
    {
      "id": 9,
      "name": "彩虹屁卡",
      "rarity": "common",
      "description": "使用此卡后，你需要连续说5分钟不间断的夸赞话，不能重复不能敷衍。",
      "usage": "当我需要肯定和赞美时使用，尤其适合因自信心不足生气时。",
      "tips": "可以提前准备一些夸赞点。真诚最重要，不要浮夸。",
      "quote": "你的真诚赞美永远能触动我的心，让我忘记为什么生气。",
      "isSearched": false
    }
  ]
}